cd_utils_logger/__init__.py
cd_utils_logger/logger_utils.py
utils_logger/__init__.py
utils_logger/logger_utils.py
cd_utils_logger-1.0.3.dist-info/LICENSE
cd_utils_logger-1.0.3.dist-info/METADATA
cd_utils_logger-1.0.3.dist-info/WHEEL
cd_utils_logger-1.0.3.dist-info/top_level.txt
cd_utils_logger-1.0.3.dist-info/RECORD
